.gpu6_7_16.sh.swp
LICENSE
MANIFEST.in
README.md
_debug.py
_init_.py
candidate.py
collect_code.py
diversity.py
generate.py
generate_prompt.py
generate_simin.py
mod_json.py
pass_k.py
pass_k_ning.py
setup.py
utils.py
./.gpu6_7_16.sh.swp
./LICENSE
./MANIFEST.in
./README.md
./_debug.py
./_init_.py
./candidate.py
./collect_code.py
./diversity.py
./generate.py
./generate_prompt.py
./generate_simin.py
./mod_json.py
./pass_k.py
./pass_k_ning.py
./setup.py
./utils.py
./.git/HEAD
./.git/config
./.git/description
./.git/index
./.git/packed-refs
./.git/hooks/applypatch-msg.sample
./.git/hooks/commit-msg.sample
./.git/hooks/fsmonitor-watchman.sample
./.git/hooks/post-update.sample
./.git/hooks/pre-applypatch.sample
./.git/hooks/pre-commit.sample
./.git/hooks/pre-merge-commit.sample
./.git/hooks/pre-push.sample
./.git/hooks/pre-rebase.sample
./.git/hooks/pre-receive.sample
./.git/hooks/prepare-commit-msg.sample
./.git/hooks/update.sample
./.git/info/exclude
./.git/logs/HEAD
./.git/logs/refs/heads/master
./.git/logs/refs/remotes/origin/HEAD
./.git/objects/pack/pack-79e759ac5ce2a1f4de2614736769c53ee5ce87c8.idx
./.git/objects/pack/pack-79e759ac5ce2a1f4de2614736769c53ee5ce87c8.pack
./.git/refs/heads/master
./.git/refs/remotes/origin/HEAD
./.idea/misc.xml
./.idea/modules.xml
./.idea/vcs.xml
./.mypy_cache/.gitignore
./.mypy_cache/CACHEDIR.TAG
./.mypy_cache/3.8/@plugins_snapshot.json
./.mypy_cache/3.8/_ast.data.json
./.mypy_cache/3.8/_ast.meta.json
./.mypy_cache/3.8/_codecs.data.json
./.mypy_cache/3.8/_codecs.meta.json
./.mypy_cache/3.8/_collections_abc.data.json
./.mypy_cache/3.8/_collections_abc.meta.json
./.mypy_cache/3.8/abc.data.json
./.mypy_cache/3.8/abc.meta.json
./.mypy_cache/3.8/builtins.data.json
./.mypy_cache/3.8/builtins.meta.json
./.mypy_cache/3.8/codecs.data.json
./.mypy_cache/3.8/codecs.meta.json
./.mypy_cache/3.8/contextlib.data.json
./.mypy_cache/3.8/contextlib.meta.json
./.mypy_cache/3.8/dataclasses.data.json
./.mypy_cache/3.8/dataclasses.meta.json
./PPM_FSE.egg-info/PKG-INFO
./PPM_FSE.egg-info/SOURCES.txt
./PPM_FSE.egg-info/dependency_links.txt
./PPM_FSE.egg-info/top_level.txt
PPM_FSE.egg-info/PKG-INFO
PPM_FSE.egg-info/SOURCES.txt
PPM_FSE.egg-info/dependency_links.txt
PPM_FSE.egg-info/top_level.txt